tests/__init__.py
tests/test_thunes.py
thunes/__init__.py
thunes/thunes.py
thunes_py-0.2a5.dist-info/LICENSE
thunes_py-0.2a5.dist-info/METADATA
thunes_py-0.2a5.dist-info/WHEEL
thunes_py-0.2a5.dist-info/top_level.txt
thunes_py-0.2a5.dist-info/RECORD
